csvy/__init__.py
csvy/_csvy.py
csvy-0.1.5.dist-info/WHEEL
csvy-0.1.5.dist-info/METADATA
csvy-0.1.5.dist-info/RECORD
