Metadata-Version: 2.1
Name: csvy
Version: 0.1.5
Summary: Convenience wrappers for the standard library csv module.
Home-page: https://gitlab.com/mgemmill-pypi/csvy
License: BSD-4-Clause
Keywords: csv
Author: Mark Gemmill
Author-email: gitlab@markgemmill.com
Requires-Python: >=3.6,<4.0
Classifier: License :: Other/Proprietary License
Classifier: Programming Language :: Python :: 3
Classifier: Programming Language :: Python :: 3 :: Only
Classifier: Programming Language :: Python :: 3.6
Classifier: Programming Language :: Python :: 3.7
Classifier: Programming Language :: Python :: 3.8
Classifier: Topic :: Software Development :: Libraries
Project-URL: Repository, https://gitlab.com/mgemmill-pypi/csvy
